ai/__init__.py
ai/batch_summarize.py
ai/llm.py
ai/llm_summarize.py
ai/llm_translate.py
ai/tts.py
config/__init__.py
config/config.py
model/__init__.py
model/article.py
model/article_extraction.py
model/article_version.py
model/feed.py
model/feed_manager.py
model/feed_parser.py
model/feed_pipeline.py
model/latest_articles.py
model/session.py
model/session_manager.py
model/tests/__init__.py
model/tests/test_feed_manager.py
plainews/__init__.py
plainews/app.py
storage/__init__.py
storage/config_dir.py
storage/stored_feeds.py
storage/stored_session.py
storage/tests/__init__.py
storage/tests/test_storage.py
transform/__init__.py
transform/article_summary.py
transform/article_transformer.py
transform/article_translator.py
transform/transformation_builder.py
ui/__init__.py
ui/article_layout.tcss
ui/article_screen.py
ui/article_view.py
ui/articles_list.py
ui/feeds_list.py
ui/feeds_list.tcss
ui/home.py
ui/home_layout.tcss
ui/latest_articles_screen.py
ui/latest_articles_view.py
ui/latest_articles_view.tcss
ui/reader_view.py
ui/reader_view.tcss
plainews-0.9.0.dist-info/LICENSE
plainews-0.9.0.dist-info/METADATA
plainews-0.9.0.dist-info/WHEEL
plainews-0.9.0.dist-info/entry_points.txt
plainews-0.9.0.dist-info/RECORD
