Metadata-Version: 2.3
Name: plainews
Version: 0.9.0
Summary: Distraction and clutter free reading
Author: Nikola Sobadjiev
Author-email: nikola@kumulintelligence.com
Requires-Python: >=3.11
Classifier: Programming Language :: Python :: 3.11
Classifier: License :: OSI Approved :: MIT License
Classifier: Operating System :: Unix
Requires-Dist: feedparser (>=6.0.11,<7.0.0)
Requires-Dist: litellm (>=1.56.10,<2.0.0)
Requires-Dist: lxml_html_clean (>=0.2.0,<0.3.0)
Requires-Dist: newspaper3k (>=0.2.8,<0.3.0)
Requires-Dist: pydantic (>=2.10.4,<3.0.0)
Requires-Dist: pydantic-settings (>=2.7.1,<3.0.0)
Requires-Dist: rich (>=13.9.4,<14.0.0)
Requires-Dist: textual (>=2.1.0,<3.0.0)
Project-URL: Homepage, https://github.com/nsobadzhiev/plainews
Project-URL: Issues, https://github.com/nsobadzhiev/plainews/issues
